ao_conventional_pre_commit/__init__.py
ao_conventional_pre_commit/format.py
ao_conventional_pre_commit/hook.py
ao_conventional_pre_commit-3.2.0.dist-info/LICENSE
ao_conventional_pre_commit-3.2.0.dist-info/METADATA
ao_conventional_pre_commit-3.2.0.dist-info/WHEEL
ao_conventional_pre_commit-3.2.0.dist-info/entry_points.txt
ao_conventional_pre_commit-3.2.0.dist-info/top_level.txt
ao_conventional_pre_commit-3.2.0.dist-info/RECORD
