Metadata-Version: 2.1
Name: ao-conventional-pre-commit
Version: 3.2.0
Summary: An AO-customized pre-commit hook that checks commit messages for Conventional Commits formatting and JIRA ticket.
Author-email: Kevin Castro <kevin@anderstonopt.com>
License: Apache License
Project-URL: code, https://github.com/anderson-optimization/ao-conventional-pre-commit
Project-URL: tracker, https://github.com/anderson-optimization/ao-conventional-pre-commit/issues
Keywords: git,pre-commit,ao-conventional-commits
Classifier: Programming Language :: Python :: 3 :: Only
Requires-Python: >=3.8
License-File: LICENSE
Provides-Extra: dev
Requires-Dist: black ; extra == 'dev'
Requires-Dist: build ; extra == 'dev'
Requires-Dist: coverage ; extra == 'dev'
Requires-Dist: flake8 ; extra == 'dev'
Requires-Dist: pre-commit ; extra == 'dev'
Requires-Dist: pytest ; extra == 'dev'
Requires-Dist: setuptools-scm ; extra == 'dev'
